ecobench/__init__.py
ecobench/model.py
ecobench/models.py
ecobench/tracker.py
ecobench/visualizer.py
ecobench-1.0.1.dist-info/licenses/LICENSE
ecobench-1.0.1.dist-info/METADATA
ecobench-1.0.1.dist-info/WHEEL
ecobench-1.0.1.dist-info/top_level.txt
ecobench-1.0.1.dist-info/RECORD
