Metadata-Version: 2.4
Name: ecobench
Version: 1.0.1
Summary: A Python library for tracking LLM usage, costs, and environmental impact
Home-page: https://github.com/KnutOplandMoen/ecobench
Author: knut Opland Moen
Author-email: Ecobench Team <contact@ecobench.dev>
Maintainer-email: Ecobench Team <contact@ecobench.dev>
License: MIT
Project-URL: Homepage, https://github.com/ecobench/ecobench
Project-URL: Documentation, https://github.com/ecobench/ecobench#readme
Project-URL: Repository, https://github.com/ecobench/ecobench
Project-URL: Bug Tracker, https://github.com/ecobench/ecobench/issues
Keywords: llm,tracking,cost,energy,environmental,monitoring,ai,machine-learning
Classifier: Development Status :: 4 - Beta
Classifier: Intended Audience :: Developers
Classifier: Intended Audience :: Science/Research
Classifier: License :: OSI Approved :: MIT License
Classifier: Operating System :: OS Independent
Classifier: Programming Language :: Python :: 3
Classifier: Programming Language :: Python :: 3.8
Classifier: Programming Language :: Python :: 3.9
Classifier: Programming Language :: Python :: 3.10
Classifier: Programming Language :: Python :: 3.11
Classifier: Programming Language :: Python :: 3.12
Classifier: Topic :: Scientific/Engineering :: Artificial Intelligence
Classifier: Topic :: Software Development :: Libraries :: Python Modules
Classifier: Topic :: System :: Monitoring
Requires-Python: >=3.8
License-File: LICENSE
Requires-Dist: numpy<2.0.0,>=1.21.0
Provides-Extra: dev
Requires-Dist: pytest>=6.0; extra == "dev"
Requires-Dist: pytest-cov>=2.0; extra == "dev"
Requires-Dist: black>=21.0; extra == "dev"
Requires-Dist: flake8>=3.8; extra == "dev"
Requires-Dist: mypy>=0.900; extra == "dev"
Requires-Dist: pre-commit>=2.0; extra == "dev"
Provides-Extra: docs
Requires-Dist: sphinx>=4.0; extra == "docs"
Requires-Dist: sphinx-rtd-theme>=1.0; extra == "docs"
Dynamic: author
Dynamic: home-page
Dynamic: license-file
Dynamic: requires-python
